Metadata-Version: 1.1
Name: geonode-notification
Version: 1.1.3
Summary: User notification management for the Django web framework
Home-page: https://github.com/GeoNode/geonode-notification
Author: James Tauber
Author-email: jtauber@jtauber.com
License: UNKNOWN
Platform: UNKNOWN
Classifier: Development Status :: 5 - Production/Stable
Classifier: Environment :: Web Environment
Classifier: Intended Audience :: Developers
Classifier: License :: OSI Approved :: MIT License
Classifier: Operating System :: OS Independent
Classifier: Programming Language :: Python :: 2.7
Classifier: Programming Language :: Python :: 3.3
Classifier: Framework :: Django
